respick/__init__.py
respick/__main__.py
respick/cli.py
respick/core.py
respick-0.1.6.dist-info/licenses/LICENSE
respick-0.1.6.dist-info/METADATA
respick-0.1.6.dist-info/WHEEL
respick-0.1.6.dist-info/entry_points.txt
respick-0.1.6.dist-info/top_level.txt
respick-0.1.6.dist-info/RECORD
