Metadata-Version: 2.4
Name: respick
Version: 0.1.6
Summary: Resistor divider picker for DCDC/LDO applications
Author-email: Jerry Zheng <JerryZheng2018@outlook.com>
License: MIT
Requires-Python: >=3.7
License-File: LICENSE
Dynamic: license-file
